unduplicate_itunes/__init__.py
unduplicate_itunes/remove_by_artist_and_title.py
unduplicate_itunes/wip/remove_by_hash.py
unduplicate_itunes/wip/remove_duplicate_itunes_songs.py
unduplicate_itunes-1.0.2.dist-info/LICENSE
unduplicate_itunes-1.0.2.dist-info/METADATA
unduplicate_itunes-1.0.2.dist-info/WHEEL
unduplicate_itunes-1.0.2.dist-info/RECORD
