Metadata-Version: 2.1
Name: unduplicate-itunes
Version: 1.0.2
Summary: Remove duplicated iTunes song files from your computer
License: MIT
Author: Ariff Jeff
Author-email: ariffjeff@icloud.com
Requires-Python: >=3.9,<4.0
Classifier: License :: OSI Approved :: MIT License
Classifier: Programming Language :: Python :: 3
Classifier: Programming Language :: Python :: 3.9
Classifier: Programming Language :: Python :: 3.10
Classifier: Programming Language :: Python :: 3.11
Requires-Dist: send2trash (>=1.8.0,<2.0.0)
Requires-Dist: tinytag (>=1.8.1,<2.0.0)
